packageapi/__init__.py
packageapi/gui.py
packageapi-0.2.1.dist-info/licenses/LICENSE
packageapi-0.2.1.dist-info/METADATA
packageapi-0.2.1.dist-info/WHEEL
packageapi-0.2.1.dist-info/entry_points.txt
packageapi-0.2.1.dist-info/top_level.txt
packageapi-0.2.1.dist-info/RECORD
