Metadata-Version: 2.4
Name: packageapi
Version: 0.2.1
Summary: A simple Tkinter-based Python package installer/checker GUI
Author-email: OptionallyBlueStudios/StuffzEZ/Stuf_y <optionallybluestudios@googlegroups.com>
License: MIT
Project-URL: Homepage, https://github.com/OptionallyBlueStudios/PackageAPI
Requires-Python: >=3.7
License-File: LICENSE
Dynamic: license-file
